conway_engine/__init__.py
conway_engine/simulation.py
conway_engine-1.0.0.dist-info/LICENSE
conway_engine-1.0.0.dist-info/METADATA
conway_engine-1.0.0.dist-info/WHEEL
conway_engine-1.0.0.dist-info/entry_points.txt
conway_engine-1.0.0.dist-info/top_level.txt
conway_engine-1.0.0.dist-info/RECORD
