Metadata-Version: 2.1
Name: conway-engine
Version: 1.0.0
Summary: Conway Engine is a Python package offering a sophisticated implementation of Conway's Game of Life, featuring the iconic Gosper Glider Gun for dynamic and explosive cellular automaton growth.
Home-page: https://github.com/vivekkdagar/conway_engine
Author: Vivek Dagar
Author-email: vivekdagar2017@gmail.com
License: GNU General Public License v3.0
License-File: LICENSE
Requires-Dist: pygame
Requires-Dist: numpy
